{
  "edition": 1020,
  "itemId": "1491710967669573983632461584275500858424839404562109",
  "name": "EvoX G6",
  "image": "https://www.wearecashcows.com/images/loot/1020.png",
  "category": "Rides",
  "rarity": "Common",
  "available": 1668042000000,
  "limit": 0,
  "attributes": [
    {
      "trait_name": "Type",
      "value": "Car"
    },
    {
      "trait_name": "Speed",
      "value": "90 MPH"
    },
    {
      "trait_name": "Horsepower",
      "value": "260 HP"
    },
    {
      "trait_name": "Passengers",
      "value": "2"
    },
    {
      "trait_name": "Origin",
      "value": "United Emerates"
    }
  ],
  "pricing": {
    "0xa61a3d600db91942E0BD36EA7f1a8f9cc7F99086": "75000000000000000000000"
  }
}